{
  "main": {
    "id": "a48fa1fba89c2cfa",
    "type": "split",
    "children": [
      {
        "id": "b91413fc68a59fe6",
        "type": "tabs",
        "children": [
          {
            "id": "4939a1814a03f05b",
            "type": "leaf",
            "state": {
              "type": "markdown",
              "state": {
                "file": "README.md",
                "mode": "source",
                "source": false
              },
              "icon": "lucide-file",
              "title": "README"
            }
          }
        ]
      }
    ],
    "direction": "vertical"
  },
  "left": {
    "id": "b7f8e2a80b6a43c6",
    "type": "split",
    "children": [
      {
        "id": "fd13ea4cc2866524",
        "type": "tabs",
        "children": [
          {
            "id": "2bb7fad36731170d",
            "type": "leaf",
            "state": {
              "type": "file-explorer",
              "state": {
                "sortOrder": "alphabetical"
              },
              "icon": "lucide-folder-closed",
              "title": "Files"
            }
          },
          {
            "id": "4f697499920efeca",
            "type": "leaf",
            "state": {
              "type": "search",
              "state": {
                "query": "",
                "matchingCase": false,
                "explainSearch": false,
                "collapseAll": false,
                "extraContext": false,
                "sortOrder": "alphabetical"
              },
              "icon": "lucide-search",
              "title": "Search"
            }
          },
          {
            "id": "ad18581ee1fe6e30",
            "type": "leaf",
            "state": {
              "type": "bookmarks",
              "state": {},
              "icon": "lucide-bookmark",
              "title": "Bookmarks"
            }
          }
        ]
      }
    ],
    "direction": "horizontal",
    "width": 300
  },
  "right": {
    "id": "93a1ad65f02cf8e5",
    "type": "split",
    "children": [
      {
        "id": "cd048a731154e7d3",
        "type": "tabs",
        "children": [
          {
            "id": "d431a4997437d09a",
            "type": "leaf",
            "state": {
              "type": "backlink",
              "state": {
                "file": "pages/Docker notes.md",
                "collapseAll": false,
                "extraContext": false,
                "sortOrder": "alphabetical",
                "showSearch": false,
                "searchQuery": "",
                "backlinkCollapsed": false,
                "unlinkedCollapsed": true
              },
              "icon": "links-coming-in",
              "title": "Backlinks for Docker notes"
            }
          },
          {
            "id": "657210697dcd9ec2",
            "type": "leaf",
            "state": {
              "type": "outgoing-link",
              "state": {
                "file": "README.md",
                "linksCollapsed": false,
                "unlinkedCollapsed": true
              },
              "icon": "links-going-out",
              "title": "Outgoing links from README"
            }
          },
          {
            "id": "5393e14511ab4c4a",
            "type": "leaf",
            "state": {
              "type": "tag",
              "state": {
                "sortOrder": "frequency",
                "useHierarchy": true
              },
              "icon": "lucide-tags",
              "title": "Tags"
            }
          },
          {
            "id": "d712b906a66a7c2c",
            "type": "leaf",
            "state": {
              "type": "outline",
              "state": {
                "file": "pages/Docker notes.md"
              },
              "icon": "lucide-list",
              "title": "Outline of Docker notes"
            }
          }
        ],
        "currentTab": 1
      }
    ],
    "direction": "horizontal",
    "width": 300,
    "collapsed": true
  },
  "left-ribbon": {
    "hiddenItems": {
      "switcher:Open quick switcher": false,
      "graph:Open graph view": false,
      "canvas:Create new canvas": false,
      "daily-notes:Open today's daily note": false,
      "templates:Insert template": false,
      "command-palette:Open command palette": false,
      "obsidian-importer:Open Importer": false
    }
  },
  "active": "4939a1814a03f05b",
  "lastOpenFiles": [
    "pages/Kubernetes/Imperative vs Declarative mode/Imperative vs Declarative mode.md",
    "assets/readme_view.webp",
    "pages/Kubernetes/Kubernetes.md",
    "README.md",
    "pages/AWS ECS/AWS ECS.md",
    "pages/First project deploy/First project deploy.md",
    "pages/Deploying Docker Containers on AWS.md",
    "pages/Docker compose.md",
    "pages/Utility containers/Utility containers.md",
    "pages/Network on docker/Network on docker.md",
    "pages/Introduction to Volumes/Introduction to Volumes.md",
    "pages/Docker - Core terminal commands.md",
    "pages/Docker notes.md",
    "pages/Docker - Core concepts/Docker - Core concepts.md",
    "assets/Untitled.png",
    "assets/Untitled 1.png",
    "assets/image 4 2.png",
    "assets/image 5.png",
    "assets/image 4.png",
    "assets/image 3 2.png",
    "assets/image 3.png",
    "assets/image 2 2.png",
    "assets/image 2.png",
    "README",
    "assets",
    "pages/Kubernetes/Imperative vs Declarative mode",
    "pages/Kubernetes",
    "pages/AWS ECS",
    "pages/First project deploy",
    "pages/Utility containers",
    "pages/Network on docker",
    "pages/Introduction to Volumes",
    "pages/Docker - Core concepts",
    "Docker notes.md",
    "Docker compose.md",
    "Docker - Core terminal commands.md",
    "Deploying Docker Containers on AWS.md",
    "Network on docker/Network on docker.md",
    "Utility containers/Utility containers.md",
    "AWS ECS/AWS ECS.md",
    "Kubernetes/Imperative vs Declarative mode/Imperative vs Declarative mode.md",
    "Kubernetes/Kubernetes.md",
    "First project deploy/First project deploy.md"
  ]
}